knit_langchain/__init__.py
knit_langchain/client/__init__.py
knit_langchain/client/auth_client.py
knit_langchain/client/http_client.py
knit_langchain/client/sdk_client.py
knit_langchain/exceptions/exceptions.py
knit_langchain/logger.py
knit_langchain/models/tools_filter.py
knit_langchain/models/tools_summary.py
knit_langchain/utils/constants.py
knit_langchain/utils/json_schema_to_pydantic.py
knit_langchain-0.1.1.dist-info/METADATA
knit_langchain-0.1.1.dist-info/WHEEL
knit_langchain-0.1.1.dist-info/RECORD
